step/__init__.py
step/functionality/__init__.py
step/functionality/base.py
step/functionality/comps/__init__.py
step/functionality/comps/model_ops.py
step/functionality/comps/trainer.py
step/functionality/cross_funcmodel.py
step/functionality/sc_funcmodel.py
step/functionality/st_funcmodel.py
step/integration.py
step/manager/__init__.py
step/manager/save.py
step/models/__init__.py
step/models/clust.py
step/models/deconv.py
step/models/distributions.py
step/models/extension.py
step/models/knn_map.py
step/models/niche/__init__.py
step/models/niche/helper.py
step/models/niche/pipeline.py
step/models/nnls.py
step/models/transcriptformer.py
step/modules/__init__.py
step/modules/decoder.py
step/modules/gnn.py
step/modules/transformer.py
step/scmodel.py
step/stmodel.py
step/utils/__init__.py
step/utils/dataset.py
step/utils/gbolt.py
step/utils/metrics.py
step/utils/misc.py
step/utils/plotting.py
step/utils/synthetics/__init__.py
step/utils/synthetics/pseudo_st.py
step_kit-0.3.dist-info/LICENSE
step_kit-0.3.dist-info/METADATA
step_kit-0.3.dist-info/WHEEL
step_kit-0.3.dist-info/RECORD
