Metadata-Version: 2.1
Name: step-kit
Version: 0.3
Summary: STEP, an acronym for Spatial Transcriptomics Embedding Procedure, is a deep learning-based tool for the analysis of single-cell RNA (scRNA-seq) and spatially resolved transcriptomics (SRT) data. STEP introduces a unified approach to process and analyze multiple samples of scRNA-seq data as well as align several sections of SRT data, disregarding location relationships. Furthermore, STEP conducts integrative analysis across different modalities like scRNA-seq and SRT.
Home-page: https://github.com/SGGb0nd/step
License: Apache-2.0
Keywords: spatial transcriptomics,single-cell RNA-seq,deep learning,scRNA-seq,SRT,step,STEP
Author: SGGb0nd
Author-email: lilounan1997@gmail.com
Requires-Python: >=3.10,<4.0
Classifier: License :: OSI Approved :: Apache Software License
Classifier: Programming Language :: Python :: 3
Classifier: Programming Language :: Python :: 3.10
Classifier: Programming Language :: Python :: 3.11
Classifier: Programming Language :: Python :: 3.12
Provides-Extra: cu117
Provides-Extra: docs
Provides-Extra: ipykernel
Provides-Extra: r
Requires-Dist: dgl (>=1.1.2,<2.0.0) ; extra == "cu117"
Requires-Dist: einops (>=0.6.0,<0.7.0)
Requires-Dist: esda (==2.5.1)
Requires-Dist: furo ; extra == "docs"
Requires-Dist: grakel
Requires-Dist: ipykernel ; extra == "ipykernel"
Requires-Dist: leidenalg (>=0.9.0,<0.10.0)
Requires-Dist: libpysal (==4.8.1)
Requires-Dist: myst-parser ; extra == "docs"
Requires-Dist: nbsphinx ; extra == "docs"
Requires-Dist: numpy (>=1.21.2,<2.0.0)
Requires-Dist: pydantic
Requires-Dist: rpy2 ; extra == "r"
Requires-Dist: scanpy (>=1.10.0,<2.0.0)
Requires-Dist: scikit-misc
Requires-Dist: sphinx ; extra == "docs"
Requires-Dist: sphinx-autoapi ; extra == "docs"
Requires-Dist: sphinx-autodoc-typehints ; extra == "docs"
Requires-Dist: sphinx-book-theme ; extra == "docs"
Requires-Dist: sphinx-copybutton ; extra == "docs"
Requires-Dist: sphinxcontrib-bibtex ; extra == "docs"
Requires-Dist: torch (>=1.13.1,<2.0.0) ; extra == "cu117"
Project-URL: Documentation, https://sggb0nd.github.io/step/
Project-URL: Repository, https://github.com/SGGb0nd/step
